<?xml version="1.0" encoding="utf-8"?>
<!DOCTYPE hibernate-mapping PUBLIC "-//Hibernate/Hibernate Mapping DTD 3.0//EN"
"http://hibernate.sourceforge.net/hibernate-mapping-3.0.dtd">
<!-- 
    Mapping file autogenerated by MyEclipse Persistence Tools
-->
<hibernate-mapping>
    <class name="com.shoppingguide.entity.Tuserrole" table="tuserrole" catalog="shoppingguidesystem">
        <id name="id" type="java.lang.Integer">
            <column name="Id" />
            <generator class="sequence" />
        </id>
        <property name="roleName" type="java.lang.String">
            <column name="RoleName" length="40" not-null="true">
                <comment>管理员角色名称</comment>
            </column>
        </property>
        <property name="remark" type="java.lang.String">
            <column name="Remark" length="65535" />
        </property>
        <set name="tuserrolepermissionsowns" inverse="true">
            <key>
                <column name="UserRoleId" not-null="true" />
            </key>
            <one-to-many class="com.shoppingguide.entity.Tuserrolepermissionsown" />
        </set>
    </class>
</hibernate-mapping>
